Metadata-Version: 2.4
Name: scCellFie
Version: 0.5.0
Summary: A tool for inferring metabolic activities from single-cell and spatial transcriptomics
Home-page: https://github.com/earmingol/scCellFie
Author: Erick Armingol
Author-email: erickarmingol@gmail.com
Classifier: Programming Language :: Python :: 3
Classifier: License :: OSI Approved :: MIT License
Classifier: Operating System :: OS Independent
License-File: LICENSE.txt
Requires-Dist: scanpy
Requires-Dist: numpy
Requires-Dist: pandas
Requires-Dist: cobra
Requires-Dist: tqdm
Requires-Dist: scipy
Requires-Dist: anndata
Requires-Dist: squidpy
Requires-Dist: networkx
Requires-Dist: geopandas
Requires-Dist: esda
Requires-Dist: matplotlib
Requires-Dist: seaborn
Requires-Dist: glasbey
Dynamic: author
Dynamic: author-email
Dynamic: classifier
Dynamic: description
Dynamic: description-content-type
Dynamic: home-page
Dynamic: license-file
Dynamic: requires-dist
Dynamic: summary
